xGeTJwT/__init__.py
xGeTJwT/xGeTJwT.py
xgetjwt-0.3.0.dist-info/licenses/LICENSE
xgetjwt-0.3.0.dist-info/METADATA
xgetjwt-0.3.0.dist-info/WHEEL
xgetjwt-0.3.0.dist-info/top_level.txt
xgetjwt-0.3.0.dist-info/RECORD
