Metadata-Version: 2.4
Name: xGeTJwT
Version: 0.3.0
Summary: JWT Token Generator for Garena API
Author: BesToPy
Author-email: abdelkarim@email.com
License: MIT
Classifier: Programming Language :: Python :: 3
Classifier: Operating System :: OS Independent
Requires-Python: >=3.6
License-File: LICENSE
Requires-Dist: requests>=2.25.0
Requires-Dist: pycryptodome>=3.10.1
Requires-Dist: protobuf>=3.20.0
Dynamic: author
Dynamic: author-email
Dynamic: classifier
Dynamic: description
Dynamic: description-content-type
Dynamic: license
Dynamic: license-file
Dynamic: requires-dist
Dynamic: requires-python
Dynamic: summary
